{
  "id": "icheon-ceramic-village",
  "name": "이천 도자기 마을 (도예원)",
  "region": "gyeonggi-south",
  "subRegion": "이천시",
  "category": "experience",
  "ageBands": ["3-6y", "6-10y"],
  "indoorOutdoor": "both",
  "priceType": "paid",
  "reservationRequired": true,
  "parking": true,
  "sourceType": "semi-official",
  "sourceUrl": "https://www.icheon.go.kr/",
  "verifiedAt": "2026-04-01",
  "lastObservedAt": "2026-04-01",
  "verificationStatus": "semi_verified",
  "description": "도자기 만들기 체험이 가능한 이천 도자기 마을. 부모와 아이가 함께하는 공예 체험.",
  "address": "경기 이천시 신둔면 도자예술로 일대",
  "operatingHours": "10:00-17:00 (업체별 상이)",
  "priceInfo": "체험 프로그램별 상이 (1인 15,000~30,000원)",
  "feedingRoom": false,
  "strollerFriendly": false,
  "rainFriendly": true,
  "stayMinutes": 120,
  "operatorType": "commercial",
  "editorNote": "업체마다 가격·시간 다름. 사전 예약 필수. 공식 홈 개별 확인 권장"
}
